scvoting/__init__.py
scvoting_vjbaskar-0.0.2.dist-info/LICENSE
scvoting_vjbaskar-0.0.2.dist-info/METADATA
scvoting_vjbaskar-0.0.2.dist-info/WHEEL
scvoting_vjbaskar-0.0.2.dist-info/top_level.txt
scvoting_vjbaskar-0.0.2.dist-info/RECORD
