Metadata-Version: 2.1
Name: scvoting-vjbaskar
Version: 0.0.2
Summary: Projection of on scRNAseq on another and voting. Sam Watcham's thesis chapter 3
Home-page: https://github.com/pypa/scvoting
Author: Vijay
Author-email: vjbaskar@gmail.com
License: UNKNOWN
Platform: UNKNOWN
Classifier: Programming Language :: Python :: 3
Classifier: License :: OSI Approved :: MIT License
Classifier: Operating System :: OS Independent
Requires-Python: >=3.6
